IcePy.cpython-312-darwin.so
slice2py.py
Glacier2/CannotCreateSessionException.py
Glacier2/IdentitySet.py
Glacier2/IdentitySet_forward.py
Glacier2/PermissionDeniedException.py
Glacier2/PermissionsVerifier.py
Glacier2/PermissionsVerifier_forward.py
Glacier2/Router.py
Glacier2/Router_forward.py
Glacier2/SSLInfo.py
Glacier2/SSLPermissionsVerifier.py
Glacier2/SSLPermissionsVerifier_forward.py
Glacier2/SSLSessionManager.py
Glacier2/SSLSessionManager_forward.py
Glacier2/Session.py
Glacier2/SessionControl.py
Glacier2/SessionControl_forward.py
Glacier2/SessionManager.py
Glacier2/SessionManager_forward.py
Glacier2/SessionNotExistException.py
Glacier2/Session_forward.py
Glacier2/StringSet.py
Glacier2/StringSet_forward.py
Glacier2/__init__.py
Glacier2/py.typed
Ice/AdapterAlreadyActiveException.py
Ice/AdapterNotFoundException.py
Ice/BTEndpointType.py
Ice/BTSEndpointType.py
Ice/Blobject.py
Ice/BoolSeq.py
Ice/Builtin.py
Ice/ByteSeq.py
Ice/Communicator.py
Ice/CompressBatch.py
Ice/Context.py
Ice/Current.py
Ice/Dispatch.py
Ice/DoubleSeq.py
Ice/EncodingVersion.py
Ice/EndpointSelectionType.py
Ice/EventLoopAdapter.py
Ice/Exception.py
Ice/FloatSeq.py
Ice/FormatType.py
Ice/Future.py
Ice/IcePyTypes.py
Ice/Identity.py
Ice/IdentitySeq.py
Ice/ImplicitContext.py
Ice/InitializationData.py
Ice/IntSeq.py
Ice/InvalidReplicaGroupIdException.py
Ice/InvocationFuture.py
Ice/LocalException.py
Ice/LocalExceptions.py
Ice/Locator.py
Ice/LocatorFinder.py
Ice/LocatorFinder_forward.py
Ice/LocatorRegistry.py
Ice/LocatorRegistry_forward.py
Ice/Locator_forward.py
Ice/LogMessage.py
Ice/LogMessageSeq.py
Ice/LogMessageType.py
Ice/LogMessageTypeSeq.py
Ice/Logger.py
Ice/LoggerAdmin.py
Ice/LoggerAdmin_forward.py
Ice/LongSeq.py
Ice/Object.py
Ice/ObjectAdapter.py
Ice/ObjectNotFoundException.py
Ice/ObjectProxySeq.py
Ice/ObjectPrx.py
Ice/ObjectPrx_forward.py
Ice/ObjectSeq.py
Ice/OperationMode.py
Ice/Process.py
Ice/ProcessLogger.py
Ice/Process_forward.py
Ice/Properties.py
Ice/PropertiesAdmin.py
zeroc_ice-3.8.0.post1.dist-info/METADATA
zeroc_ice-3.8.0.post1.dist-info/WHEEL
zeroc_ice-3.8.0.post1.dist-info/entry_points.txt
zeroc_ice-3.8.0.post1.dist-info/top_level.txt
zeroc_ice-3.8.0.post1.dist-info/RECORD
