Metadata-Version: 2.4
Name: zeroc-ice
Version: 3.8.0.post1
Summary: Ice is a comprehensive RPC framework with support for Python, C++, .NET, Java, JavaScript and more.
Author-email: "ZeroC, Inc." <info@zeroc.com>
License-Expression: GPL-2.0-only
Project-URL: Homepage, https://zeroc.com/ice
Project-URL: Repository, https://github.com/zeroc-ice/ice
Project-URL: Documentation, https://code.zeroc.com/ice/3.8/api/python/index.html
Project-URL: Issues, https://github.com/zeroc-ice/ice/issues
Project-URL: Changelog, https://github.com/zeroc-ice/ice/blob/main/CHANGELOG-3.8.md
Keywords: ice,RPC
Classifier: Development Status :: 3 - Alpha
Classifier: Intended Audience :: Developers
Classifier: Programming Language :: Python :: 3
Classifier: Programming Language :: Python :: 3.12
Classifier: Operating System :: OS Independent
Classifier: Topic :: Software Development :: Libraries :: Application Frameworks
Requires-Python: >=3.12
